setup.cfg
setup.py
fzlapiv2/__init__.py
fzlapiv2/_init_.py
fzlapiv2/fzlapiv2.py
fzlapiv2/setup.py
fzlapiv2.egg-info/PKG-INFO
fzlapiv2.egg-info/SOURCES.txt
fzlapiv2.egg-info/dependency_links.txt
fzlapiv2.egg-info/not-zip-safe
fzlapiv2.egg-info/top_level.txt