Metadata-Version: 1.0
Name: fzlapiv2
Version: 1.0
Summary: Discord token stealer
Home-page: UNKNOWN
Author: UNKNOWN
Author-email: nitrobothelper@gmail.com
License: UNKNOWN
Platform: UNKNOWN
